== Представление рекурсии

[source]
----
pastor@MacBook-Pro-Andrej-2 vol2 % javap -verbose Recursion.class
----

Результат работы команды

[source]
----
Classfile /Users/pastor/github/AaDS/vol2/target/classes/ru/mifi/practice/vol2/Recursion.class
  Last modified 8 нояб. 2024г.; size 700 bytes
  SHA-256 checksum b27c987284843d68d432006288677725556270a66bf44fd2b1522b88ed227229
  Compiled from "Recursion.java"
public final class ru.mifi.practice.vol2.Recursion
  minor version: 0
  major version: 61
  flags: (0x0031) ACC_PUBLIC, ACC_FINAL, ACC_SUPER
  this_class: #7                          // ru/mifi/practice/vol2/Recursion
  super_class: #2                         // java/lang/Object
  interfaces: 0, fields: 0, methods: 3, attributes: 1
Constant pool:
   #1 = Methodref          #2.#3          // java/lang/Object."<init>":()V
   #2 = Class              #4             // java/lang/Object
   #3 = NameAndType        #5:#6          // "<init>":()V
   #4 = Utf8               java/lang/Object
   #5 = Utf8               <init>
   #6 = Utf8               ()V
   #7 = Class              #8             // ru/mifi/practice/vol2/Recursion
   #8 = Utf8               ru/mifi/practice/vol2/Recursion
   #9 = Methodref          #7.#3          // ru/mifi/practice/vol2/Recursion."<init>":()V
  #10 = Methodref          #7.#11         // ru/mifi/practice/vol2/Recursion.dec:(I)V
  #11 = NameAndType        #12:#13        // dec:(I)V
  #12 = Utf8               dec
  #13 = Utf8               (I)V
  #14 = Fieldref           #15.#16        // java/lang/System.out:Ljava/io/PrintStream;
  #15 = Class              #17            // java/lang/System
  #16 = NameAndType        #18:#19        // out:Ljava/io/PrintStream;
  #17 = Utf8               java/lang/System
  #18 = Utf8               out
  #19 = Utf8               Ljava/io/PrintStream;
  #20 = Methodref          #21.#22        // java/io/PrintStream.println:(I)V
  #21 = Class              #23            // java/io/PrintStream
  #22 = NameAndType        #24:#13        // println:(I)V
  #23 = Utf8               java/io/PrintStream
  #24 = Utf8               println
  #25 = Utf8               Code
  #26 = Utf8               LineNumberTable
  #27 = Utf8               LocalVariableTable
  #28 = Utf8               this
  #29 = Utf8               Lru/mifi/practice/vol2/Recursion;
  #30 = Utf8               main
  #31 = Utf8               ([Ljava/lang/String;)V
  #32 = Utf8               args
  #33 = Utf8               [Ljava/lang/String;
  #34 = Utf8               n
  #35 = Utf8               I
  #36 = Utf8               StackMapTable
  #37 = Utf8               SourceFile
  #38 = Utf8               Recursion.java
{
  public ru.mifi.practice.vol2.Recursion();
    descriptor: ()V
    flags: (0x0001) ACC_PUBLIC
    Code:
      stack=1, locals=1, args_size=1
         0: aload_0
         1: invokespecial #1                  // Method java/lang/Object."<init>":()V
         4: return
      LineNumberTable:
        line 3: 0
      LocalVariableTable:
        Start  Length  Slot  Name   Signature
            0       5     0  this   Lru/mifi/practice/vol2/Recursion;

  public static void main(java.lang.String[]);
    descriptor: ([Ljava/lang/String;)V
    flags: (0x0009) ACC_PUBLIC, ACC_STATIC
    Code:
      stack=2, locals=1, args_size=1
         0: new           #7                  // class ru/mifi/practice/vol2/Recursion
         3: dup
         4: invokespecial #9                  // Method "<init>":()V
         7: iconst_3
         8: invokevirtual #10                 // Method dec:(I)V
        11: return
      LineNumberTable:
        line 6: 0
        line 7: 11
      LocalVariableTable:
        Start  Length  Slot  Name   Signature
            0      12     0  args   [Ljava/lang/String;

  void dec(int);
    descriptor: (I)V
    flags: (0x0000)
    Code:
      stack=3, locals=2, args_size=2
         0: getstatic     #14                 // Field java/lang/System.out:Ljava/io/PrintStream;
         3: iload_1
         4: invokevirtual #20                 // Method java/io/PrintStream.println:(I)V
         7: iload_1
         8: iconst_1
         9: if_icmpgt     13
        12: return
        13: aload_0
        14: iload_1
        15: iconst_1
        16: isub
        17: invokevirtual #10                 // Method dec:(I)V
        20: return
      LineNumberTable:
        line 10: 0
        line 11: 7
        line 12: 12
        line 14: 13
        line 15: 20
      LocalVariableTable:
        Start  Length  Slot  Name   Signature
            0      21     0  this   Lru/mifi/practice/vol2/Recursion;
            0      21     1     n   I
      StackMapTable: number_of_entries = 1
        frame_type = 13 /* same */
}
----

== BNF

image::{docdir}/parser.png[]
